synthSportPlayer/__init__.py
synthSportPlayer/sportplayer.py
synthSportPlayer/utils.py
synthSportPlayer_DJS-1.2.0.dist-info/LICENSE
synthSportPlayer_DJS-1.2.0.dist-info/METADATA
synthSportPlayer_DJS-1.2.0.dist-info/WHEEL
synthSportPlayer_DJS-1.2.0.dist-info/top_level.txt
synthSportPlayer_DJS-1.2.0.dist-info/RECORD
