Metadata-Version: 2.1
Name: synthSportPlayer-DJS
Version: 1.2.0
Summary: A package to simulate synthetic sports players/teams
Home-page: https://github.com/DrJStrudwick/Synthetic-Sport-Player
Author: Dr J Strudwick
License: UNKNOWN
Project-URL: Bug Tracker, https://github.com/DrJStrudwick/Synthetic-Sport-Player/issues
Project-URL: Documentation, https://synthetic-sport-player.readthedocs.io/en/latest/index.html
Platform: UNKNOWN
Classifier: Programming Language :: Python :: 3
Classifier: License :: OSI Approved :: MIT License
Classifier: Operating System :: OS Independent
Requires-Python: >=3.6
